spectral_encoding/__init__.py
spectral_encoding/data/sensors.csv
spectral_encoding/datamodel.py
spectral_encoding/main.py
spectral_encoding/utils.py
spectral_encoding-0.0.1.dist-info/LICENSE
spectral_encoding-0.0.1.dist-info/WHEEL
spectral_encoding-0.0.1.dist-info/METADATA
spectral_encoding-0.0.1.dist-info/RECORD
