Metadata-Version: 2.1
Name: spectral-encoding
Version: 0.0.1
Summary: This is a template repository for Python projects that use Poetry for their dependency management.
Home-page: https://github.com/csaybar/spectral-encoding
Author: Cesar Aybar
Author-email: fcesar.aybar@uv.es
Requires-Python: >=3.8,<4.0
Classifier: Programming Language :: Python :: 3
Classifier: Programming Language :: Python :: 3.8
Classifier: Programming Language :: Python :: 3.9
Classifier: Programming Language :: Python :: 3.10
Project-URL: Documentation, https://csaybar.github.io/spectral-encoding/
Project-URL: Repository, https://github.com/csaybar/spectral-encoding
